timing_sim/hdl/chips/hc04_not.v
`timescale 1ns/1ns

module hc04_not (
    input wire [5:0] In,
    output wire [5:0] Out
);

    assign #9 Out = ~In;

endmodule

timing_sim/hdl/chips/hc32_or.v
`timescale 1ns/1ns

module hc32_or (
    input wire [3:0] A,
    input wire [3:0] B,
    output wire [3:0] Out
);

    assign #10 Out = A | B;

endmodule

timing_sim/hdl/chips/hc08_and.v
`timescale 1ns/1ns

module hc08_and (
    input wire [3:0] A,
    input wire [3:0] B,
    output wire [3:0] Out
);

    assign #10 Out = A & B;

endmodule

timing_sim/hdl/pc_parts/jmp_logic.v
`timescale 1ns/1ns

module jmp_logic (
    input wire [0:0] Zero,
    input wire [0:0] Negative,
    input wire [15:0] Instruction,

    output wire [0:0] Jmp
    );

wire [3:0] and_a_in;
wire [3:0] and_b_in;
wire [3:0] and_out;
wire [3:0] or_a_in;
wire [3:0] or_b_in;
wire [3:0] or_out;
wire [5:0] not_in;
wire [5:0] not_out;


hc08_and my_and (
.A(and_a_in),
.B(and_b_in),
.Out(and_out)
);   

hc32_or my_or (
.A(or_a_in),
.B(or_b_in),
.Out(or_out)
);

hc04_not my_not (
.In(not_in),
.Out(not_out)
);

// jmp zero

assign and_a_in[0] = Zero;
assign and_b_in[0] = Instruction[1];

// jmp negative

assign and_a_in[1] = Negative;
assign and_b_in[1] = Instruction[2];

// jmp positive

assign or_a_in[0] = Zero;
assign or_b_in[0] = Negative;

assign not_in[0] = or_out[0];

assign and_a_in[2] = not_out[0];
assign and_b_in[2] = Instruction[0];

// alles or-en

assign or_a_in[1] = and_out[0];
assign or_b_in[1] = and_out[1];

assign or_a_in[2] = or_out[1];
assign or_b_in[2] = and_out[2];

// nur wenn C-Instruction

assign and_a_in[3] = or_out[2];
assign and_b_in[3] = Instruction[15];

assign Jmp = and_out[3];


endmodule

timing_sim/test/test_jmp_logic.v
`timescale 1ns/1ns

module jmp_logic_tb ();

    reg [0:0] Zero_tb;
    reg [0:0] Negative_tb;
    reg [15:0] Instruction_tb;

    wire [0:0] Jmp_tb;

    jmp_logic my_jmp_logic (
        .Zero(Zero_tb),
        .Negative(Negative_tb),
        .Instruction(Instruction_tb),
        .Jmp(Jmp_tb)
    );

    initial begin
        $dumpfile("timing_result.vcd");
        $dumpvars(0,jmp_logic_tb);

        // positive 

        Zero_tb = 0;
        Negative_tb = 0;
        
        Instruction_tb = 16'b1000_0000_0000_0000;
        #100
        Instruction_tb = 16'b1000_0000_0000_0001;
        #100
        Instruction_tb = 16'b1000_0000_0000_0010;
        #100
        Instruction_tb = 16'b1000_0000_0000_0100;
        #100
        
        Zero_tb = 0;
        Negative_tb = 1;
        
        Instruction_tb = 16'b1000_0000_0000_0000;
        #100
        Instruction_tb = 16'b1000_0000_0000_0001;
        #100
        Instruction_tb = 16'b1000_0000_0000_0010;
        #100
        Instruction_tb = 16'b1000_0000_0000_0100;
        #100
        
        Zero_tb = 1;
        Negative_tb = 0;
        
        Instruction_tb = 16'b1000_0000_0000_0000;
        #100
        Instruction_tb = 16'b1000_0000_0000_0001;
        #100
        Instruction_tb = 16'b1000_0000_0000_0010;
        #100
        Instruction_tb = 16'b1000_0000_0000_0100;
        #100
        
        $finish;

    end
endmodule

timing_sim/timing_result.vcd
$date
	Sun May 10 17:36:24 2026
$end
$version
	Icarus Verilog
$end
$timescale
	1ns
$end
$scope module jmp_logic_tb $end
$var wire 1 ! Jmp_tb $end
$var reg 16 " Instruction_tb [15:0] $end
$var reg 1 # Negative_tb $end
$var reg 1 $ Zero_tb $end
$scope module my_jmp_logic $end
$var wire 16 % Instruction [15:0] $end
$var wire 1 # Negative $end
$var wire 1 $ Zero $end
$var wire 4 & or_out [3:0] $end
$var wire 4 ' or_b_in [3:0] $end
$var wire 4 ( or_a_in [3:0] $end
$var wire 6 ) not_out [5:0] $end
$var wire 6 * not_in [5:0] $end
$var wire 4 + and_out [3:0] $end
$var wire 4 , and_b_in [3:0] $end
$var wire 4 - and_a_in [3:0] $end
$var wire 1 ! Jmp $end
$scope module my_and $end
$var wire 4 . A [3:0] $end
$var wire 4 / B [3:0] $end
$var wire 4 0 Out [3:0] $end
$upscope $end
$scope module my_not $end
$var wire 6 1 In [5:0] $end
$var wire 6 2 Out [5:0] $end
$upscope $end
$scope module my_or $end
$var wire 4 3 A [3:0] $end
$var wire 4 4 B [3:0] $end
$var wire 4 5 Out [3:0] $end
$upscope $end
$upscope $end
$upscope $end
$enddefinitions $end
$comment Show the parameter values. $end
$dumpall
$end
#0
$dumpvars
bx 5
bzxx0 4
bzxx0 3
bx 2
bzx 1
bx 0
b1000 /
bx00 .
bx00 -
b1000 ,
bx +
bzx *
bx )
bzxx0 (
bzxx0 '
bx &
b1000000000000000 %
0$
0#
b1000000000000000 "
x!
$end
#10
bz000 '
bz000 4
bzx00 (
bzx00 3
bz0 *
bz0 1
bx000 +
bx000 0
bx0 &
bx0 5
#19
bx100 -
bx100 .
bx1 )
bx1 2
#20
bz000 (
bz000 3
bx00 &
bx00 5
#30
b100 -
b100 .
bx000 &
bx000 5
#40
0!
b0 +
b0 0
#100
b1100 ,
b1100 /
b1000000000000001 "
b1000000000000001 %
#110
bz100 '
bz100 4
b100 +
b100 0
#120
b1100 -
b1100 .
bx100 &
bx100 5
#130
1!
b1100 +
b1100 0
#200
b1001 ,
b1001 /
b1000000000000010 "
b1000000000000010 %
#210
bz000 '
bz000 4
b1000 +
b1000 0
#220
b100 -
b100 .
bx000 &
bx000 5
#230
0!
b0 +
b0 0
#300
b1010 ,
b1010 /
b1000000000000100 "
b1000000000000100 %
#400
b1000 ,
b1000 /
b110 -
b110 .
bz001 '
bz001 4
b1000000000000000 "
b1000000000000000 %
1#
#410
bz1 *
bz1 1
bx001 &
bx001 5
#419
b10 -
b10 .
bx0 )
bx0 2
#500
b1100 ,
b1100 /
b1000000000000001 "
b1000000000000001 %
#600
b1001 ,
b1001 /
b1000000000000010 "
b1000000000000010 %
#700
b1010 ,
b1010 /
b1000000000000100 "
b1000000000000100 %
#710
bz011 '
bz011 4
b10 +
b10 0
#720
bz100 (
bz100 3
bx011 &
bx011 5
#730
b1010 -
b1010 .
bx111 &
bx111 5
#740
1!
b1010 +
b1010 0
#800
b1000 ,
b1000 /
bz010 '
bz010 4
b1001 -
b1001 .
bz101 (
bz101 3
b1000000000000000 "
b1000000000000000 %
0#
1$
#810
bz000 '
bz000 4
b1000 +
b1000 0
#820
bz001 (
bz001 3
bx101 &
bx101 5
#830
b1 -
b1 .
bx001 &
bx001 5
#840
0!
b0 +
b0 0
#900
b1100 ,
b1100 /
b1000000000000001 "
b1000000000000001 %
#1000
b1001 ,
b1001 /
b1000000000000010 "
b1000000000000010 %
#1010
bz011 (
bz011 3
b1 +
b1 0
#1020
bz111 (
bz111 3
bx011 &
bx011 5
#1030
b1001 -
b1001 .
bx111 &
bx111 5
#1040
1!
b1001 +
b1001 0
#1100
b1010 ,
b1010 /
b1000000000000100 "
b1000000000000100 %
#1110
bz101 (
bz101 3
b1000 +
b1000 0
#1120
bz001 (
bz001 3
bx101 &
bx101 5
#1130
b1 -
b1 .
bx001 &
bx001 5
#1140
0!
b0 +
b0 0
