timing_sim/hdl/chips/at28c256_15_rom.v
`timescale 1ns/1ns

module at28c256_15_rom #( 
    parameter ROM_FILE = ""
)(
    input logic [14:0] Address,
    output logic [7:0] Data
);

logic [7:0] memory [0:32747];

initial begin
    if (ROM_FILE != "") begin
        $readmemh(ROM_FILE, memory);
    end
end


assign #150 Data = memory[ Address];

endmodule

timing_sim/hdl/pc_parts/rom_16bit.v
`timescale 1ns/1ns

module rom_16bit #(
    parameter FILE_16BIT = "data/rom_16bit.txt"
)(
    input wire [14:0] address,
    output wire [15:0] data
);

wire [7:0] data_high;
wire [7:0] data_low;

at28c256_15_rom #( .ROM_FILE("") ) rom_low (
    .Address(address),
    .Data(data_low)
);

at28c256_15_rom #( .ROM_FILE("") ) rom_high (
    .Address(address),
    .Data(data_high)
);

logic [15:0] temp_mem [ 0:32767];

initial begin
    for (int i=0; i<32768; i++) begin
        temp_mem[i] = 16'h0000;
    end

    if (FILE_16BIT !== "" ) begin
        $readmemh(FILE_16BIT,temp_mem);
    end

    for( int i = 0; i < 32767; i++) begin
        rom_high.memory[i] = temp_mem[i][15:8];
        rom_low.memory[i] = temp_mem[i][7:0];
    end
end

assign data = {data_high, data_low};

endmodule

timing_sim/test/test_rom_16.sv
`timescale 1ns/1ns

module test_rom_tb ();

    logic [14:0] Address_tb;
    logic [15:0] Data_tb;
    logic [0:0]  Clk_tb;

    rom_16bit my_rom (
        .address(Address_tb),
        .data(Data_tb)
    );

    initial begin
        Clk_tb = 0;
        forever #200 Clk_tb = ~Clk_tb;
    end

    initial begin
        $dumpfile("timing_result.vcd");
        $dumpvars(0,test_rom_tb);
    
        
        Address_tb = 0;
        repeat (10) begin
            @(posedge Clk_tb);
            Address_tb = Address_tb + 15'h0001;
        end

        $finish;
    end

endmodule

timing_sim/timing_result.vcd
$date
	Mon May 11 23:28:21 2026
$end
$version
	Icarus Verilog
$end
$timescale
	1ns
$end
$scope module test_rom_tb $end
$var wire 16 ! Data_tb [15:0] $end
$var reg 15 " Address_tb [14:0] $end
$var reg 1 # Clk_tb $end
$scope module my_rom $end
$var wire 15 $ address [14:0] $end
$var wire 8 % data_low [7:0] $end
$var wire 8 & data_high [7:0] $end
$var wire 16 ' data [15:0] $end
$var parameter 144 ( FILE_16BIT $end
$scope module rom_high $end
$var wire 15 ) Address [14:0] $end
$var wire 8 * Data [7:0] $end
$var parameter 8 + ROM_FILE $end
$upscope $end
$scope module rom_low $end
$var wire 15 , Address [14:0] $end
$var wire 8 - Data [7:0] $end
$var parameter 8 . ROM_FILE $end
$upscope $end
$scope begin $ivl_for_loop0 $end
$var integer 32 / i [31:0] $end
$upscope $end
$scope begin $ivl_for_loop1 $end
$var integer 32 0 i [31:0] $end
$upscope $end
$upscope $end
$upscope $end
$enddefinitions $end
$comment Show the parameter values. $end
$dumpall
b0 .
b0 +
b11001000110000101110100011000010010111101110010011011110110110101011111001100010011011001100010011010010111010000101110011101000111100001110100 (
$end
#0
$dumpvars
b111111111111111 0
b1000000000000000 /
bx -
b0 ,
bx *
b0 )
bx '
bx &
bx %
b0 $
0#
b0 "
bx !
$end
#150
b0 !
b0 '
b0 %
b0 -
b0 &
b0 *
#200
b1 "
b1 $
b1 )
b1 ,
1#
#350
b1100100 !
b1100100 '
b1100100 %
b1100100 -
#400
0#
#600
b10 "
b10 $
b10 )
b10 ,
1#
#750
b1110110000010000 !
b1110110000010000 '
b11101100 &
b11101100 *
b10000 %
b10000 -
#800
0#
#1000
b11 "
b11 $
b11 )
b11 ,
1#
#1150
b0 !
b0 '
b0 &
b0 *
b0 %
b0 -
#1200
0#
#1400
b100 "
b100 $
b100 )
b100 ,
1#
#1550
b1110001100001000 !
b1110001100001000 '
b11100011 &
b11100011 *
b1000 %
b1000 -
#1600
0#
#1800
b101 "
b101 $
b101 )
b101 ,
1#
#1950
b10 !
b10 '
b0 &
b0 *
b10 %
b10 -
#2000
0#
#2200
b110 "
b110 $
b110 )
b110 ,
1#
#2350
b1110110000010000 !
b1110110000010000 '
b11101100 &
b11101100 *
b10000 %
b10000 -
#2400
0#
#2600
b111 "
b111 $
b111 )
b111 ,
1#
#2750
b1 !
b1 '
b0 &
b0 *
b1 %
b1 -
#2800
0#
#3000
b1000 "
b1000 $
b1000 )
b1000 ,
1#
#3150
b1110001100001000 !
b1110001100001000 '
b11100011 &
b11100011 *
b1000 %
b1000 -
#3200
0#
#3400
b1001 "
b1001 $
b1001 )
b1001 ,
1#
#3550
b0 !
b0 '
b0 &
b0 *
b0 %
b0 -
#3600
0#
#3800
b1010 "
b1010 $
b1010 )
b1010 ,
1#
